digiarch/__init__.py
digiarch/_data/blacklist.json
digiarch/_data/digiarch_recurse.ps1
digiarch/_data/ext_map.json
digiarch/cli.py
digiarch/core/ArchiveFileRel.py
digiarch/core/__init__.py
digiarch/core/checksums.py
digiarch/core/custom_sigs.json
digiarch/core/fix_file_exts.py
digiarch/core/identify_files.py
digiarch/core/path_utils.py
digiarch/core/text_file.txt
digiarch/core/utils.py
digiarch/database/__init__.py
digiarch/database/db.py
digiarch/exceptions.py
digiarch/models/__init__.py
digiarch/models/file_data.py
digiarch/models/metadata.py
digiarch-0.9.10.dist-info/entry_points.txt
digiarch-0.9.10.dist-info/LICENSE
digiarch-0.9.10.dist-info/WHEEL
digiarch-0.9.10.dist-info/METADATA
digiarch-0.9.10.dist-info/RECORD
