Metadata-Version: 2.1
Name: digiarch
Version: 0.9.10
Summary: Tools for the Digital Archive Project at Aarhus Stadsarkiv
Home-page: https://stadsarkiv.aarhus.dk/
License: GPL-3.0
Keywords: archiving,preservation,identification
Author: Aryan Muhammadi Landi
Author-email: arml@aarhus.dk
Requires-Python: >=3.8,<4.0
Classifier: License :: OSI Approved :: GNU General Public License v3 (GPLv3)
Classifier: Programming Language :: Python :: 3
Classifier: Programming Language :: Python :: 3.8
Classifier: Programming Language :: Python :: 3.9
Requires-Dist: acamodels (>=0.5.3,<0.6.0)
Requires-Dist: click (>=7.0,<8.0)
Requires-Dist: dacite (>=1.0,<2.0)
Requires-Dist: databases[sqlite] (>=0.3.2,<0.5.0)
Requires-Dist: natsort (>=7.0.1,<8.0.0)
Requires-Dist: pydantic (>=1.6.1,<2.0.0)
Requires-Dist: python-dateutil (>=2.8.1,<3.0.0)
Requires-Dist: requests (>=2.23.0,<3.0.0)
Requires-Dist: sqlalchemy (>=1.3,<1.4)
Requires-Dist: sqlalchemy_utils (>=0.36.8,<0.38.0)
Requires-Dist: tqdm (>=4.36,<5.0)
Project-URL: Repository, https://github.com/aarhusstadsarkiv/digiarch
